tcrudge/__init__.py
tcrudge/decorators.py
tcrudge/exceptions.py
tcrudge/handlers.py
tcrudge/models.py
tcrudge/response.py
tcrudge/__pycache__/__init__.cpython-35.pyc
tcrudge/__pycache__/decorators.cpython-35.pyc
tcrudge/__pycache__/exceptions.cpython-35.pyc
tcrudge/__pycache__/handlers.cpython-35.pyc
tcrudge/__pycache__/models.cpython-35.pyc
tcrudge/__pycache__/response.cpython-35.pyc
tcrudge/utils/__init__.py
tcrudge/utils/json.py
tcrudge/utils/schema.py
tcrudge/utils/validation.py
tcrudge/utils/xhtml_escape.py
tcrudge/utils/__pycache__/__init__.cpython-35.pyc
tcrudge/utils/__pycache__/json.cpython-35.pyc
tcrudge/utils/__pycache__/schema.cpython-35.pyc
tcrudge/utils/__pycache__/validation.cpython-35.pyc
tcrudge-0.9.11.dist-info/DESCRIPTION.rst
tcrudge-0.9.11.dist-info/METADATA
tcrudge-0.9.11.dist-info/RECORD
tcrudge-0.9.11.dist-info/WHEEL
tcrudge-0.9.11.dist-info/metadata.json
tcrudge-0.9.11.dist-info/top_level.txt
