Metadata-Version: 2.0
Name: tcrudge
Version: 0.9.11
Summary: Tornado RESTful API with Peewee
Home-page: https://github.com/CodeTeam/tcrudge
Author: Code Team
Author-email: saborisov@sberned.ru
License: MIT
Platform: UNKNOWN
Classifier: Development Status :: 3 - Alpha
Classifier: Environment :: Web Environment
Classifier: Intended Audience :: Developers
Classifier: License :: OSI Approved :: MIT License
Classifier: Operating System :: OS Independent
Classifier: Programming Language :: Python
Classifier: Programming Language :: Python :: 3.5
Classifier: Topic :: Internet :: WWW/HTTP
Requires-Dist: aiopg (==0.10.0)
Requires-Dist: jsonschema (==2.5.1)
Requires-Dist: msgpack-python (==0.4.8)
Requires-Dist: peewee (==2.8.3)
Requires-Dist: peewee-async (==0.5.5)
Requires-Dist: psycopg2 (==2.6.2)
Requires-Dist: tornado (==4.4.2)
Provides-Extra: tests
Requires-Dist: coverage (==4.2); extra == 'tests'
Requires-Dist: py (==1.4.31); extra == 'tests'
Requires-Dist: pytest (==3.0.2); extra == 'tests'
Requires-Dist: pytest-cov (==2.3.1); extra == 'tests'
Requires-Dist: pytest-env (==0.6.0); extra == 'tests'
Requires-Dist: pytest-tornado (==0.4.5); extra == 'tests'
